exceptdrucker/README.MD
exceptdrucker/__init__.py
exceptdrucker/requirements.txt
exceptdrucker/thirdparty.json
exceptdrucker-0.10.dist-info/LICENSE.rst
exceptdrucker-0.10.dist-info/METADATA
exceptdrucker-0.10.dist-info/WHEEL
exceptdrucker-0.10.dist-info/top_level.txt
exceptdrucker-0.10.dist-info/RECORD
