Metadata-Version: 2.1
Name: exceptdrucker
Version: 0.10
Summary: Module for colorful printing and error handling.
Home-page: https://github.com/hansalemaos/exceptdrucker
Author: Johannes Fischer
Author-email: aulasparticularesdealemaosp@gmail.com
License: MIT
Keywords: error,exception
Classifier: Development Status :: 4 - Beta
Classifier: Programming Language :: Python :: 3 :: Only
Classifier: Programming Language :: Python :: 3.10
Classifier: Topic :: Software Development :: Libraries :: Python Modules
Classifier: Topic :: Utilities
License-File: LICENSE.rst
